abs_utils/azure_service_bus/__init__.py
abs_utils/azure_service_bus/azure_service_bus.py
abs_utils/azure_service_bus/event_decorator.py
abs_utils/constants/__init__.py
abs_utils/constants/endpoint_constants.py
abs_utils/constants/event_constants.py
abs_utils/logger/__init__.py
abs_utils/logger/logger.py
abs_utils/schemas/__init__.py
abs_utils/schemas/fields_schema/__init__.py
abs_utils/schemas/fields_schema/common_schema.py
abs_utils/schemas/fields_schema/field_schema.py
abs_utils/schemas/libs/__init__.py
abs_utils/schemas/libs/extend_enum.py
abs_utils/schemas/libs/make_optional.py
abs_utils/socket_io/__init__.py
abs_utils/socket_io/server.py
abs_utils-0.4.3.dist-info/METADATA
abs_utils-0.4.3.dist-info/WHEEL
abs_utils-0.4.3.dist-info/RECORD
