Metadata-Version: 2.3
Name: abs-utils
Version: 0.4.3
Summary: AutoBridge Systems Utility Library
Author: AutoBridgeSystems
Author-email: info@autobridgesystems.com
Requires-Python: >=3.11,<4.0
Classifier: Programming Language :: Python :: 3
Classifier: Programming Language :: Python :: 3.11
Classifier: Programming Language :: Python :: 3.12
Classifier: Programming Language :: Python :: 3.13
Requires-Dist: abs-exception-core (>=0.2.2,<0.3.0)
Requires-Dist: aiohttp (>=3.11.18,<4.0.0)
Requires-Dist: azure-identity (>=1.22.0,<2.0.0)
Requires-Dist: azure-servicebus (>=7.14.2,<8.0.0)
Requires-Dist: fastapi[standard] (>=0.115.2)
Requires-Dist: python-socketio (>=5.13.0,<6.0.0)
